mcblmplss/__init__.py
mcblmplss/census.py
mcblmplss/client.py
mcblmplss/server.py
mcblmplss/mixins/__init__.py
mcblmplss/mixins/acec.py
mcblmplss/mixins/grazing.py
mcblmplss/mixins/mining_claims.py
mcblmplss/mixins/plss.py
mcblmplss/mixins/recreation.py
mcblmplss/mixins/surface_management.py
mcblmplss/mixins/wild_horses.py
mcblmplss/mixins/wild_rivers.py
mcblmplss/mixins/wilderness.py
mcblmplss-2026.1.25.dist-info/METADATA
mcblmplss-2026.1.25.dist-info/WHEEL
mcblmplss-2026.1.25.dist-info/entry_points.txt
mcblmplss-2026.1.25.dist-info/licenses/LICENSE
mcblmplss-2026.1.25.dist-info/RECORD
