Metadata-Version: 2.4
Name: mcblmplss
Version: 2026.1.25
Summary: MCP server for querying BLM land data: PLSS, land manager, mining claims, grazing, wild horses, recreation, wilderness, rivers, and ACECs
Project-URL: Homepage, https://git.supported.systems/MCP/mcblmplss
Project-URL: Repository, https://git.supported.systems/MCP/mcblmplss
Project-URL: Issues, https://git.supported.systems/MCP/mcblmplss/issues
Author-email: Ryan Malloy <ryan@supported.systems>
License-Expression: MIT
License-File: LICENSE
Keywords: acec,blm,cadastral,fastmcp,gis,grazing,land-ownership,land-survey,mcp,mining-claims,plss,public-lands,recreation,surface-management,wild-horses,wild-rivers,wilderness
Classifier: Development Status :: 4 - Beta
Classifier: Intended Audience :: Developers
Classifier: License :: OSI Approved :: MIT License
Classifier: Programming Language :: Python :: 3.11
Classifier: Programming Language :: Python :: 3.12
Classifier: Programming Language :: Python :: 3.13
Classifier: Topic :: Scientific/Engineering :: GIS
Requires-Python: >=3.11
Requires-Dist: fastmcp>=2.13.2
Requires-Dist: httpx>=0.28.1
